{
  "COMMONS": {
    "FULLSCREEN_MODE": "Schermo intero",
    "WINDOW_MODE": "Modalità finestra",
    "PROFILE_IMAGE": "Immagine del profilo dell'utente registrato o le sue iniziali  ",
    "LICENCES": "Licenze",
    "PACKAGES": "Pacchetti",
    "CREDITS": "Crediti",
    "TERMS_OF_USE": "Termini di utilizzo",
    "PRIVACY_POLICY": "Informativa sulla privacy",
    "TEXT_EDITOR": "Editor di Testo",
    "LICENCES_TEXT": "Il codice sorgente dell’applicazione DEWETRA e di tutte le Opere derivate (MyDEWETRA, MyDEWETRA Word, e tutte le applicazioni della suite) è rilasciato in modalità Open Source sotto la licenza EUPL. \nIl codice integra le seguenti componenti di terzi parti a loro volta distribuite con licenze open source compatibili con la licenza EUPL. \n\"In caso di conflitto tra gli obblighi del licenziatario derivanti dalla licenza EUPL, e quelli derivanti dalle licenze delle componenti integrate, ai sensi della clausola di compatibilità “prevalgono gli obblighi prescritti dalla licenza compatibile\"."
  },
  "CONFIRM": {
    "DEFAULT_TITLE": "Conferma",
    "DEFAULT_MESSAGE": "Sei sicuro di voler procedere?",
    "WARNING": "Attenzione",
    "DOMAIN_CHANGED": "Il dominio è cambiato, la pagina verrà ricaricata.",
    "YES": "Sì",
    "NO": "No",
    "OK": "OK"
  },
  "MENU_SIDEBAR": {
    "non-mostrare": "Non mostrare",
    "menu-risorse": "Risorse",
    "menu_post_evento": "Post-evento",
    "menu-pianificazione": "Pianificazione",
    "menu-planning": "Pianificazione",
    "menu-monitoraggio": "Monitoraggio",
    "menu-comunicazione": "Comunicazione",
    "gestione_emergenze": "Gestione Emergenze",
    "admin": "Admin",
    "null": "",
    "CREDITS": "Crediti",
    "DEWIKI": "Dewiki",
    "ADMIN": "Admin"
  },
  "TIME_PICKER": {
    "HOURS": "Ore",
    "MINUTES": "Minuti",
    "ENTER_DATE_RANGE": "Inserisci range di date",
    "START_DATE": "Data iniziale",
    "END_DATE": "Data finale",
    "CANCEL": "Annulla",
    "APPLY": "Conferma",
    "RESTORE_TO_NOW": "Ripristina ad ora",
    "APPLY_CHANGES": "Applica cambiamenti",
    "EXPAND": "Espandi",
    "MINIMIZE": "Minimizza"
  },
  "TIMEBAR":{
    "NOW": "Adesso"
  },
  "NOTIFICATIONS": {
    "NOTIFICATION_SYSTEM": "Sistema di Notifiche",
    "NO_NOTIFICATIONS_RECEIVED": "Nessuna notifica ricevuta"
  },
  "FILE_DROP": {
    "FILE_EXCEEDS_SIZE_LIMIT": "Il file supera il limite di dimensione consentito. Massima dimensione consentita:"
  },
  "ERRORS": {
    "PERMISSION_DENIED": "Spiacenti, non hai il permesso per accedere a questa piattaforma.",
    "CONTACT_FOCAL_POINT": "Contatta il tuo referente per richiedere l'accesso.",
    "UNABLE_TO_LOAD": "Impossibile connettersi al server. Riprova più tardi.",
    "INTERNAL_SERVER_ERROR": "Si è verificato un errore interno del server.",
    "UNEXPECTED_ERROR": "Si è verificato un errore imprevisto:"
  },
  "NEW_VERSION_AVAILABLE": "Nuova versione disponibile. Vuoi ricarica la pagina ora?"
}
